odoo8_addon_website_hr_department-8.0.0.1.0.99.dev15-py2.7-nspkg.pth
odoo8_addon_website_hr_department-8.0.0.1.0.99.dev15.dist-info/DESCRIPTION.rst
odoo8_addon_website_hr_department-8.0.0.1.0.99.dev15.dist-info/METADATA
odoo8_addon_website_hr_department-8.0.0.1.0.99.dev15.dist-info/RECORD
odoo8_addon_website_hr_department-8.0.0.1.0.99.dev15.dist-info/WHEEL
odoo8_addon_website_hr_department-8.0.0.1.0.99.dev15.dist-info/metadata.json
odoo8_addon_website_hr_department-8.0.0.1.0.99.dev15.dist-info/namespace_packages.txt
odoo8_addon_website_hr_department-8.0.0.1.0.99.dev15.dist-info/top_level.txt
odoo_addons/website_hr_department/README.rst
odoo_addons/website_hr_department/__init__.py
odoo_addons/website_hr_department/__openerp__.py
odoo_addons/website_hr_department/controllers.py
odoo_addons/website_hr_department/models.py
odoo_addons/website_hr_department/data/websiste_hr_department_data.xml
odoo_addons/website_hr_department/i18n/ca.po
odoo_addons/website_hr_department/i18n/de.po
odoo_addons/website_hr_department/i18n/el_GR.po
odoo_addons/website_hr_department/i18n/es.po
odoo_addons/website_hr_department/i18n/eu.po
odoo_addons/website_hr_department/i18n/fr.po
odoo_addons/website_hr_department/i18n/it.po
odoo_addons/website_hr_department/i18n/pt_BR.po
odoo_addons/website_hr_department/i18n/sl.po
odoo_addons/website_hr_department/i18n/tr.po
odoo_addons/website_hr_department/i18n/website_hr_department.pot
odoo_addons/website_hr_department/security/ir.model.access.csv
odoo_addons/website_hr_department/security/website_hr_department.xml
odoo_addons/website_hr_department/static/description/icon.png
odoo_addons/website_hr_department/static/src/css/website_hr_department.css
odoo_addons/website_hr_department/views/website_hr_department.xml
